django_enum/__init__.py
django_enum/__init__.pyc
django_enum/enum.py
django_enum/enum.pyc
django_enum/fields.pyc
django_enum/tests.pyc
django_enums/__init__.py
django_enums/__init__.pyc
django_enums/enum.py
django_enums/enum.pyc
django_enums/fields.pyc
django_enums/serializers.py
django_enums/tests.pyc
django_enums/db/__init__.py
django_enums/db/fields.py
django_enums/forms/__init__.py
django_enums/forms/fields.py
django_enums-0.1.9.dist-info/DESCRIPTION.rst
django_enums-0.1.9.dist-info/METADATA
django_enums-0.1.9.dist-info/RECORD
django_enums-0.1.9.dist-info/WHEEL
django_enums-0.1.9.dist-info/metadata.json
django_enums-0.1.9.dist-info/top_level.txt
