Metadata-Version: 2.0
Name: django-enums
Version: 0.1.9
Summary: A simple Enum class and EnumField for Django models.
Home-page: https://github.com/hikaruhorie/django-enums
Author: Hikaru Horie
Author-email: hikaru@horie.to
License: MIT License
Download-URL: https://github.com/hikaruhorie/django-enums/tarball/0.1.9
Keywords: django,enum,field,status,state,choices,form,model
Platform: any
Classifier: Environment :: Web Environment
Classifier: Framework :: Django
Classifier: Framework :: Django :: 1.8
Classifier: Framework :: Django :: 1.9
Classifier: Framework :: Django :: 1.10
Classifier: Intended Audience :: Developers
Classifier: License :: OSI Approved :: MIT License
Classifier: Operating System :: OS Independent
Classifier: Programming Language :: Python
Classifier: Programming Language :: Python :: 3
Classifier: Topic :: Internet :: WWW/HTTP
Classifier: Topic :: Internet :: WWW/HTTP :: Dynamic Content
Requires-Dist: django
